zfs_autobackup/BlockHasher.py
zfs_autobackup/CachedProperty.py
zfs_autobackup/CliBase.py
zfs_autobackup/CmdPipe.py
zfs_autobackup/ExecuteNode.py
zfs_autobackup/LogConsole.py
zfs_autobackup/LogStub.py
zfs_autobackup/Thinner.py
zfs_autobackup/ThinnerRule.py
zfs_autobackup/TreeHasher.py
zfs_autobackup/ZfsAuto.py
zfs_autobackup/ZfsAutobackup.py
zfs_autobackup/ZfsAutoverify.py
zfs_autobackup/ZfsCheck.py
zfs_autobackup/ZfsDataset.py
zfs_autobackup/ZfsNode.py
zfs_autobackup/ZfsPool.py
zfs_autobackup/__init__.py
zfs_autobackup/__main__.py
zfs_autobackup/compressors.py
zfs_autobackup/util.py
zfs_autobackup-3.3.dist-info/LICENSE
zfs_autobackup-3.3.dist-info/METADATA
zfs_autobackup-3.3.dist-info/WHEEL
zfs_autobackup-3.3.dist-info/entry_points.txt
zfs_autobackup-3.3.dist-info/top_level.txt
zfs_autobackup-3.3.dist-info/RECORD
