Metadata-Version: 2.1
Name: zfs_autobackup
Version: 3.3
Summary: ZFS autobackup is used to periodicly backup ZFS filesystems to other locations. It tries to be the most friendly to use and easy to debug ZFS backup tool.
Home-page: https://github.com/psy0rz/zfs_autobackup
Author: Edwin Eefting
Author-email: edwin@datux.nl
Classifier: Programming Language :: Python :: 2
Classifier: Programming Language :: Python :: 3
Classifier: License :: OSI Approved :: GNU General Public License v3 (GPLv3)
Classifier: Operating System :: OS Independent
Requires-Python: >=2.7
License-File: LICENSE
Requires-Dist: colorama
Requires-Dist: argparse
